{
  "version": "7",
  "dialect": "postgresql",
  "entries": [
    {
      "idx": 0,
      "version": "7",
      "when": 1784071640503,
      "tag": "0000_goofy_siren",
      "breakpoints": true
    },
    {
      "idx": 1,
      "version": "7",
      "when": 1784079092525,
      "tag": "0001_auth_plane",
      "breakpoints": true
    },
    {
      "idx": 2,
      "version": "7",
      "when": 1784113037160,
      "tag": "0002_mushy_machine_man",
      "breakpoints": true
    },
    {
      "idx": 3,
      "version": "7",
      "when": 1784129123394,
      "tag": "0003_smooth_ironclad",
      "breakpoints": true
    },
    {
      "idx": 4,
      "version": "7",
      "when": 1784144395600,
      "tag": "0004_puzzling_titania",
      "breakpoints": true
    },
    {
      "idx": 5,
      "version": "7",
      "when": 1784151186083,
      "tag": "0005_daily_maginty",
      "breakpoints": true
    },
    {
      "idx": 6,
      "version": "7",
      "when": 1784168696280,
      "tag": "0006_breezy_onslaught",
      "breakpoints": true
    }
  ]
}
